> **Warning**  
> This is Work in Progress. I tried by best to accurately map all opcodes but there are 
> probably still some issues left

| Messiah Opcode | Python 2.7 Opcode | Name | DESC| 
|---|---|---|---|
|   0 |  63 | BINARY_RSHIFT |
|   1 |  24 | BINARY_SUBTRACT |
|   2 |  55 | INPLACE_ADD |
|   3 |  60 | STORE_SUBSCR |
|   4 |  79 | INPLACE_OR |
|   5 |  80 | BREAK_LOOP |
|   6 |   - | POP_THREE | Expand to `POP_TOP POP_TOP POP_TOP`
|   7 |   - | RETURN_SUBSCR |
|   8 |   - | POP_TWO | Expand to `POP_TOP POP_TOP`
|   9 |   9 | NOP |
|  10 |  10 | UNARY_POSITIVE |
|  11 |  11 | UNARY_NEGATIVE |
|  12 |  12 | UNARY_NOT |
|  13 |  13 | UNARY_CONVERT |
|  14 |   - | UNUSED |
|  15 |  15 | UNARY_INVERT |
|  16 |  -  | UNUSED |
|  17 |  -  | UNUSED |
|  18 |  -  | UNUSED |
|  19 |  19 | BINARY_POWER |
|  20 |  56 | INPLACE_SUBTRACT |
|  21 |  78 | INPLACE_XOR |
|  22 |  21 | BINARY_DIVIDE |
|  23 |  58 | INPLACE_DIVIDE |
|  24 |  25 | BINARY_SUBSCR |
|  26 |  26 | BINARY_FLOOR_DIVIDE |
|  27 |  27 | BINARY_TRUE_DIVIDE |
|  28 |  28 | INPLACE_FLOOR_DIVIDE |
|  29 |  29 | INPLACE_TRUE_DIVIDE |
|  30 |  30 | SLICE |
|  31 |  31 | SLICE_1 |
|  32 |  32 | SLICE_2 |
|  33 |  33 | SLICE_3 |
|  34 |   - | UNUSED |
|  35 |   - | UNUSED |
|  36 |   - | UNUSED |
|  37 |   - | UNUSED |
|  38 |   - | UNUSED |
|  39 |   - | UNUSED |
|  40 |  40 | STORE_SLICE |
|  41 |  41 | STORE_SLICE_1 |
|  42 |  42 | STORE_SLICE_2 |
|  43 |  43 | STORE_SLICE_3 |
|  44 |   - | UNUSED |
|  45 |   - | UNUSED |
|  46 |   - | UNUSED |
|  47 |   - | UNUSED |
|  48 |   - | UNUSED |
|  49 |   - | LOAD_LOCALS_RETURN_VALUE |
|  50 |  50 | DELETE_SLICE |
|  51 |  51 | DELETE_SLICE_1 |
|  52 |  52 | DELETE_SLICE_2 |
|  53 |  53 | DELETE_SLICE_3 |
|  54 |  84 | IMPORT_STAR |
|  55 |  66 | BINARY_OR |
|  56 |   5 | ROT_FOUR |
|  57 |  64 | BINARY_AND |
|  58 |   2 | ROT_TWO |
|  59 |  68 | GET_ITER |
|  60 |  57 | INPLACE_MULTIPLY |
|  61 |  62 | BINARY_LSHIFT |
|  62 |   3 | ROT_THREE |
|  63 |  59 | INPLACE_MODULO |
|  64 |  67 | INPLACE_POWER |
|  65 |  65 | BINARY_XOR |
|  66 |  76 | INPLACE_RSHIFT |
|  67 |  85 | EXEC_STMT |
|  68 |   1 | POP_TOP |
|  69 |   - | POP_TOP_POP_BLOCK |
|  70 |  70 | PRINT_EXPR |
|  71 |  71 | PRINT_ITEM |
|  72 |  72 | PRINT_NEWLINE |
|  73 |  73 | PRINT_ITEM_TO |
|  74 |  74 | PRINT_NEWLINE_TO |
|  75 |  61 | DELETE_SUBSCR |
|  76 |  82 | LOAD_LOCALS |
|  77 |  89 | BUILD_CLASS |
|  78 |  54 | STORE_MAP |
|  79 |  86 | YIELD_VALUE |
|  80 |  20 | BINARY_MULTIPLY |
|  81 |  81 | WITH_CLEANUP |
|  82 |  87 | POP_BLOCK |
|  83 |  22 | BINARY_MODULO |
|  84 |   4 | DUP_TOP |
|  85 |  75 | INPLACE_LSHIFT |
|  86 |  77 | INPLACE_AND |
|  87 |  88 | END_FINALLY |
|  88 |  83 | RETURN_VALUE |
|  89 |  23 | BINARY_ADD |
|  90 | 119 | CONTINUE_LOOP |
|  91 | 135 | LOAD_CLOSURE |
|  92 |  92 | UNPACK_SEQUENCE |
|  93 | 105 | BUILD_MAP |
|  94 | 114 | POP_JUMP_IF_FALSE |
|  95 | 124 | LOAD_FAST |
|  96 |  98 | DELETE_GLOBAL |
|  97 | 126 | DELETE_FAST |
|  98 | 146 | SET_ADD |
|  99 | 103 | BUILD_LIST |
| 100 | 100 | LOAD_CONST |
| 101 | 101 | LOAD_NAME |
| 102 | 102 | BUILD_TUPLE |
| 103 | 125 | STORE_FAST |
| 104 | 115 | POP_JUMP_IF_TRUE |
| 105 | 120 | SETUP_LOOP |
| 106 |  97 | STORE_GLOBAL |
| 107 |  96 | DELETE_ATTR |
| 108 | 108 | IMPORT_NAME |
| 109 | 109 | IMPORT_FROM |
| 110 | 110 | JUMP_FORWARD |
| 111 | 111 | JUMP_IF_FALSE_OR_POP |
| 112 | 112 | JUMP_IF_TRUE_OR_POP |
| 113 | 113 | JUMP_ABSOLUTE |
| 114 | 106 | LOAD_ATTR |
| 115 |  99 | DUP_TOPX |
| 116 | 116 | LOAD_GLOBAL |
| 117 |  -  | RETURN_CONST | Expand to `LOAD_CONST RETURN_VALUE`
| 118 | 118 | POP_TOP_
| 119 | 134 | MAKE_CLOSURE |
| 120 |  91 | DELETE_NAME |
| 121 |  93 | FOR_ITER |
| 122 | 147 | MAP_ADD |
| 123 |   - | POP_TOP_JUMP_FORWARD |
| 124 |  94 | LIST_APPEND |
| 125 | 136 | LOAD_DEREF |
| 126 |  95 | STORE_ATTR |
| 127 |  -  | LOAD_CONST_BINARY_SUBSCR |
| 128 |  -  | POP_TOP_LOAD_FAST |
| 129 |  -  | LOAD_CONST_STORE_MAP |
| 130 | 130 | RAISE_VARARGS |
| 131 | 131 | CALL_FUNCTION |
| 132 | 132 | MAKE_FUNCTION |
| 133 | 133 | BUILD_SLICE |
| 134 | 104 | BUILD_SET |
| 135 |  90 | STORE_NAME |
| 136 | 137 | STORE_DEREF |
| 137 | 121 | SETUP_EXCEPT |
| 138 |   - | CALL_FUNCTION_POP_TOP |
| 139 |  -  | POP_TOP_LOAD_CONST |
| 140 | 140 | CALL_FUNCTION_VAR |
| 141 | 141 | CALL_FUNCTION_KW |
| 142 | 142 | CALL_FUNCTION_VAR_KW |
| 143 | 143 | SETUP_WITH |
| 144 |  -  | UNUSED |
| 145 | 145 | EXTENDED_ARG |
| 146 | 107 | COMPARE_OP |
| 147 | 122 | SETUP_FINALLY |
| 148 |  -  | UNUSED |
| 149 |  -  | UNUSED |
| 150 |  -  | LOAD_CONST_LOAD_CONST |
| 151 |  -  | STORE_FAST_LOAD_FAST |
| 152 |  -  | LOAD_ATTR_LOAD_GLOBAL | TODO: Verify
| 153 |  -  | LOAD_FAST_CALL_FUNCTION_POP_TOP |
| 154 |  -  | COMPARE_OP_JUMP_IF_FALSE |
| 155 |  -  | LOAD_CONST_CALL_FUNCTION |
| 156 |  -  | LOAD_FAST_LOAD_CONST |
| 157 |  -  | STORE_NAME_LOAD_CONST |
| 158 |  -  | LOAD_ATTR_LOAD_FAST |
| 159 |  -  | MAKE_FUNCTION_STORE_NAME |
| 160 |  -  | LOAD_ATTR_CALL_FUNCTION |
| 161 |  -  | LOAD_CONST_COMPARE_OP |
| 162 |  -  | LOAD_ATTR_LOAD_ATTR |
| 163 |  -  | SKIP_CONST |
| 164 |  -  | LOAD_CONST_LOAD_CONST_BUILD_TUPLE |
| 165 |  -  | LOAD_GLOBAL_CALL_FUNCTION |
| 166 |  -  | LOAD_CONST_LOAD_FAST |
| 167 |  -  | STORE_FAST_LOAD_GLOBAL |
| 168 |  -  | LOAD_FAST_CALL_FUNCTION |
| 169 |  -  | CALL_FUNCTION_STORE_FAST |
| 170 |  -  | LOAD_FAST_LOAD_ATTR |
| 171 |  -  | LOAD_ATTR_CALL_FUNCTION_POP_TOP |
| 172 |  -  | LOAD_FAST_LOAD_FAST |
| 173 |  -  | LOAD_FAST_ZERO_LOAD_CONST | TODO: impl/verify |
| 174 |  -  | LOAD_FAST_STORE_ATTR | TODO: impl/verify |
| 175 |  -  | LOAD_CONST_LOAD_CONST_STORE_MAP |
| 176 |  -  | LOAD_GLOBAL_CALL_FUNCTION_POP_TOP |
| 177 |  -  | LOAD_GLOBAL_LOAD_FAST |
| 178 |  -  | CALL_FUNCTION_POP_TOP_LOAD_FAST |
| 179 |  -  | CALL_FUNCTION_CALL_FUNCTION |
| 180 |  -  | LOAD_CONST_MAKE_FUNCTION | 
| 181 |  -  | LOAD_CONST_IMPORT_NAME |
| 182 |  -  | LOAD_FAST_LOAD_CONST_BINARY_SUBSCR_LOAD_FAST_LOAD_CONST_BINARY_SUBSCR_CALL_FUNCTION | TODO: verify
| 183 |  -  | UNUSED |
| 184 |  -  | UNUSED |
| 185 |  -  | UNUSED |
| 186 |  -  | UNUSED |
| 187 |  -  | UNUSED |
| 188 |  -  | LOAD_GLOBAL_LOAD_ATTR_LOAD_FAST_LOAD_ATTR_LOAD_FAST_LOAD_FAST |
| 189 |  -  | LOAD_GLOBAL_LOAD_ATTR_LOAD_ATTR_LOAD_GLOBAL_LOAD_ATTR_LOAD_ATTR |
| 190 |  -  | LOAD_FAST_LOAT_ATTR_LOAD_CONST_LOAD_CONST_CALL_FUNCTION | TODO: verify
| 191 |  -  | LOAD_GLOABL_LOAD_ATTR_LOAD_ATTR_COMPARE_OP_LOAD_FAST |
| 192 |  -  | UNUSED |
| 193 |  -  | LOAD_FAST_LOAD_ATTR_LOAD_FAST_CALL_FUNCTION |
| 194 |  -  | LOAD_FAST_LOAD_ATTR_LOAD_FAST_LOAD_ATTR |
| 195 |  -  | LOAD_FAST_LOAD_FAST_LOAD_FAST_CALL_FUNCTION |
| 196 |  -  | LOAD_ATTR_LOAD_FAST_LOAD_FAST_CALL_FUNCTION |
| 197 |  -  | LOAD_FAST_LOAD_ATTR_LOAD_ATTR |
| 198 |  -  | LOAD_FAST_LOAD_ATTR_CALL_FUNCTION |
| 199 |  -  | LOAD_FAST_LOAD_ATTR_RETURN_VALUE |
| 200 |  -  | LOAD_FAST_LOAD_ATTR_JUMP_IF_FALSE |
| 201 |  -  | LOAD_FAST_LOAD_FAST_LOAD_FAST_LOAD_FAST_LOAD_FAST_LOAD_FAST |
| 202 |  -  | LOAD_FAST_LOAD_FAST_LOAD_FAST_LOAD_FAST |
| 203 |  -  | LOAD_FAST_LOAD_ATTR_LOAD_FAST |
| 204 |  -  | LOAD_GLOBAL_LOAD_ATTR_LOAD_ATTR |
| 205 |  -  | LOAD_FAST_LOAD_ATTR_LOAD_CONST |
| 206 |  -  | LOAD_GLOBAL_LOAD_FAST_LOAD_CONST |
| 207 |  -  | LOAD_FAST_LOAD_FAST_POP_JUMP_IF_FALSE |
| 208 |  -  | STORE_FAST_LOAD_FAST_LOAD_CONST_COMPARE_OP |
| 209 |  -  | LOAD_FAST_LOAD_CONST_COMPARE_OP_LOAD_FAST |
| 210 |  -  | LOAD_DEREF_LOAD_ATTR_LOAD_FAST_BINARY_SUBSCR |
| 211 |  -  | STORE_FAST_LOAD_FAST_POP_JUMP_IF_FALSE |
| 212 |  -  | LOAD_FAST_LOAD_CONST_BINARY_SUBSCR |
| 213 |  -  | LOAD_ATTR_LOAD_FAST_CALL_FUNCTION |
| 214 |  -  | UNUSED |
| 215 |  -  | POP_TOP_LOAD_CONST_RETURN_VALUE |
| 216 |  -  | LOAD_GLOBAL_LOAD_ATTR_LOAD_FAST |
| 217 |  -  | CALL_FUNCTION_POP_TOP_JUMP_ABSOLUTE |
| 218 |  -  | STORE_FAST_LOAD_FAST_LOAD_FAST |
| 219 |  -  | LOAD_GLOBAL_LOAD_ATTR |
| 220 |  -  | LOAD_DEREF_LOAD_ATTR |
| 221 |  -  | LOAD_FAST_STORE_FAST |
| 222 |  -  | LOAD_FAST_POP_JUMP_IF_FALSE |
| 223 |  -  | LOAD_ATTR_COMPARE_OP |
| 224 |  -  | STORE_FAST_STORE_FAST |
| 225 |  -  | POP_JUMP_IF_FALSE_2 |
| 226 |  -  | LOAD_FAST_POP_JUMP_IF_TRUE |
| 227 |  -  | LOAD_CONST_STORE_FAST |
| 228 |  -  | LOAD_FAST_RETURN_VALUE |
| 229 |  -  | LOAD_FAST_LOAD_GLOBAL |
| 230 |  -  | LOAD_GLOBAL_RETURN_VALUE |
| 231 |  -  | LOAD_FAST_BUILD_TUPLE_STORE_FAST |
| 232 |  -  | STORE_FAST_LOAD_FAST_LOAD_GLOBAL |
